Workbook

Sheet Dashboard
G1: DASHBOARD DE SYNTHESE CONSOLIDEE
A3: KPI | B3: IFRS | C3: US GAAP | D3: UK GAAP
A4: Résultat Net | B4: =Financial_Statements!C13 -> 4285683 | C4: =Financial_Statements!D13 -> 4310683 | D4: =Financial_Statements!E13 -> 4295683
A5: Total Actif | B5: =SUM(Financial_Statements!C17:C22) -> 2987456 | C5: =SUM(Financial_Statements!D17:D22) -> 2962456 | D5: =SUM(Financial_Statements!E17:E22) -> 2977456

Sheet TB_Mere_IFRS
A1: ID | B1: Compte | C1: Type | D1: Catégorie | E1: Solde_IFRS
A2: 1000 | B2: Trésorerie | C2: Actif | D2: Actif Courant | E2: 131958
A3: 1100 | B3: Créances Clients | C3: Actif | D3: Actif Courant | E3: 156867
A4: 1110 | B4: Créances Inter-compagnies | C4: Actif | D4: Actif Courant | E4: 50000
A5: 1200 | B5: Stocks | C5: Actif | D5: Actif Courant | E5: 375838
A6: 1300 | B6: Immobilisations Corporelles (PPE) | C6: Actif | D6: Actif Non Courant | E6: 269178
A7: 1305 | B7: Amortissements PPE | C7: Actif | D7: Actif Non Courant | E7: 129879
A8: 1310 | B8: Droit d'utilisation (IFRS 16) | C8: Actif | D8: Actif Non Courant | E8: 120268
A9: 1315 | B9: Amortissement Droit d'utilisation | C9: Actif | D9: Actif Non Courant | E9: 217892
A10: 1400 | B10: Immobilisations Incorporelles | C10: Actif | D10: Actif Non Courant | E10: 64886
A11: 1405 | B11: Amortissements Incorporelles | C11: Actif | D11: Actif Non Courant | E11: 147337
A12: 1410 | B12: Goodwill | C12: Actif | D12: Actif Non Courant | E12: 485602
A13: 1500 | B13: Actifs d'impôt différé | C13: Actif | D13: Actif Non Courant | E13: 440410
... A37: 7000 | B37: Impôts sur les bénéfices | C37: Charge | D37: Impôts | E37: 442752

Sheet TB_FilialeA_IFRS
A1: ID | B1: Compte | C1: Type | D1: Catégorie | E1: Solde_IFRS
A2: 1000 | B2: Trésorerie | C2: Actif | D2: Actif Courant | E2: 259342
A3: 1100 | B3: Créances Clients | C3: Actif | D3: Actif Courant | E3: 287869
A4: 1110 | B4: Créances Inter-compagnies | C4: Actif | D4: Actif Courant | E4: 50000
A5: 1200 | B5: Stocks | C5: Actif | D5: Actif Courant | E5: 27730
A6: 1300 | B6: Immobilisations Corporelles (PPE) | C6: Actif | D6: Actif Non Courant | E6: 202476
A7: 1305 | B7: Amortissements PPE | C7: Actif | D7: Actif Non Courant | E7: 392050
A8: 1310 | B8: Droit d'utilisation (IFRS 16) | C8: Actif | D8: Actif Non Courant | E8: 204278
A9: 1315 | B9: Amortissement Droit d'utilisation | C9: Actif | D9: Actif Non Courant | E9: 156449
A10: 1400 | B10: Immobilisations Incorporelles | C10: Actif | D10: Actif Non Courant | E10: 476515
A11: 1405 | B11: Amortissements Incorporelles | C11: Actif | D11: Actif Non Courant | E11: 139130
A12: 1410 | B12: Goodwill | C12: Actif | D12: Actif Non Courant | E12: 56203
A13: 1500 | B13: Actifs d'impôt différé | C13: Actif | D13: Actif Non Courant | E13: 230374
... A37: 7000 | B37: Impôts sur les bénéfices | C37: Charge | D37: Impôts | E37: 80255

Sheet TB_FilialeB_IFRS
A1: ID | B1: Compte | C1: Type | D1: Catégorie | E1: Solde_IFRS
A2: 1000 | B2: Trésorerie | C2: Actif | D2: Actif Courant | E2: 433835
A3: 1100 | B3: Créances Clients | C3: Actif | D3: Actif Courant | E3: 76149
A4: 1110 | B4: Créances Inter-compagnies | C4: Actif | D4: Actif Courant | E4: 50000
A5: 1200 | B5: Stocks | C5: Actif | D5: Actif Courant | E5: 233833
A6: 1300 | B6: Immobilisations Corporelles (PPE) | C6: Actif | D6: Actif Non Courant | E6: 327482
A7: 1305 | B7: Amortissements PPE | C7: Actif | D7: Actif Non Courant | E7: 413951
A8: 1310 | B8: Droit d'utilisation (IFRS 16) | C8: Actif | D8: Actif Non Courant | E8: 232108
A9: 1315 | B9: Amortissement Droit d'utilisation | C9: Actif | D9: Actif Non Courant | E9: 42622
A10: 1400 | B10: Immobilisations Incorporelles | C10: Actif | D10: Actif Non Courant | E10: 87647
A11: 1405 | B11: Amortissements Incorporelles | C11: Actif | D11: Actif Non Courant | E11: 498570
A12: 1410 | B12: Goodwill | C12: Actif | D12: Actif Non Courant | E12: 481284
A13: 1500 | B13: Actifs d'impôt différé | C13: Actif | D13: Actif Non Courant | E13: 185597
... A37: 7000 | B37: Impôts sur les bénéfices | C37: Charge | D37: Impôts | E37: 367993

Sheet Consolidation_IFRS
A1: ID | B1: Compte | C1: Type | D1: Catégorie | E1: Mere_IFRS | F1: FilialeA_IFRS | G1: FilialeB_IFRS | H1: Eliminations | I1: IFRS_Consolide
A2: 1000 | B2: Trésorerie | C2: Actif | D2: Actif Courant | E2: =SUMIF(TB_Mere_IFRS!A:A, A2, TB_Mere_IFRS!E:E) -> 131958 | F2: =SUMIF(TB_FilialeA_IFRS!A:A, A2, TB_FilialeA_IFRS!E:E) -> 259342 | G2: =SUMIF(TB_FilialeB_IFRS!A:A, A2, TB_FilialeB_IFRS!E:E) -> 433835 | H2: 0 | I2: =SUM(E2:H2) -> 825135
A3: 1100 | B3: Créances Clients | C3: Actif | D3: Actif Courant | E3: =SUMIF(TB_Mere_IFRS!A:A, A3, TB_Mere_IFRS!E:E) -> 156867 | F3: =SUMIF(TB_FilialeA_IFRS!A:A, A3, TB_FilialeA_IFRS!E:E) -> 287869 | G3: =SUMIF(TB_FilialeB_IFRS!A:A, A3, TB_FilialeB_IFRS!E:E) -> 76149 | H3: 0 | I3: =SUM(E3:H3) -> 520885
A4: 1110 | B4: Créances Inter-compagnies | C4: Actif | D4: Actif Courant | E4: =SUMIF(TB_Mere_IFRS!A:A, A4, TB_Mere_IFRS!E:E) -> 50000 | F4: =SUMIF(TB_FilialeA_IFRS!A:A, A4, TB_FilialeA_IFRS!E:E) -> 50000 | G4: =SUMIF(TB_FilialeB_IFRS!A:A, A4, TB_FilialeB_IFRS!E:E) -> 50000 | H4: =-(E4+F4+G4) -> -150000 | I4: =SUM(E4:H4) -> 0
A5: 1200 | B5: Stocks | C5: Actif | D5: Actif Courant | E5: =SUMIF(TB_Mere_IFRS!A:A, A5, TB_Mere_IFRS!E:E) -> 375838 | F5: =SUMIF(TB_FilialeA_IFRS!A:A, A5, TB_FilialeA_IFRS!E:E) -> 27730 | G5: =SUMIF(TB_FilialeB_IFRS!A:A, A5, TB_FilialeB_IFRS!E:E) -> 233833 | H5: 0 | I5: =SUM(E5:H5) -> 637401
A6: 1300 | B6: Immobilisations Corporelles (PPE) | C6: Actif | D6: Actif Non Courant | E6: =SUMIF(TB_Mere_IFRS!A:A, A6, TB_Mere_IFRS!E:E) -> 269178 | F6: =SUMIF(TB_FilialeA_IFRS!A:A, A6, TB_FilialeA_IFRS!E:E) -> 202476 | G6: =SUMIF(TB_FilialeB_IFRS!A:A, A6, TB_FilialeB_IFRS!E:E) -> 327482 | H6: 0 | I6: =SUM(E6:H6) -> 799136
A7: 1305 | B7: Amortissements PPE | C7: Actif | D7: Actif Non Courant | E7: =SUMIF(TB_Mere_IFRS!A:A, A7, TB_Mere_IFRS!E:E) -> 129879 | F7: =SUMIF(TB_FilialeA_IFRS!A:A, A7, TB_FilialeA_IFRS!E:E) -> 392050 | G7: =SUMIF(TB_FilialeB_IFRS!A:A, A7, TB_FilialeB_IFRS!E:E) -> 413951 | H7: 0 | I7: =SUM(E7:H7) -> 935880
A8: 1310 | B8: Droit d'utilisation (IFRS 16) | C8: Actif | D8: Actif Non Courant | E8: =SUMIF(TB_Mere_IFRS!A:A, A8, TB_Mere_IFRS!E:E) -> 120268 | F8: =SUMIF(TB_FilialeA_IFRS!A:A, A8, TB_FilialeA_IFRS!E:E) -> 204278 | G8: =SUMIF(TB_FilialeB_IFRS!A:A, A8, TB_FilialeB_IFRS!E:E) -> 232108 | H8: 0 | I8: =SUM(E8:H8) -> 556654
A9: 1315 | B9: Amortissement Droit d'utilisation | C9: Actif | D9: Actif Non Courant | E9: =SUMIF(TB_Mere_IFRS!A:A, A9, TB_Mere_IFRS!E:E) -> 217892 | F9: =SUMIF(TB_FilialeA_IFRS!A:A, A9, TB_FilialeA_IFRS!E:E) -> 156449 | G9: =SUMIF(TB_FilialeB_IFRS!A:A, A9, TB_FilialeB_IFRS!E:E) -> 42622 | H9: 0 | I9: =SUM(E9:H9) -> 416963
A10: 1400 | B10: Immobilisations Incorporelles | C10: Actif | D10: Actif Non Courant | E10: =SUMIF(TB_Mere_IFRS!A:A, A10, TB_Mere_IFRS!E:E) -> 64886 | F10: =SUMIF(TB_FilialeA_IFRS!A:A, A10, TB_FilialeA_IFRS!E:E) -> 476515 | G10: =SUMIF(TB_FilialeB_IFRS!A:A, A10, TB_FilialeB_IFRS!E:E) -> 87647 | H10: 0 | I10: =SUM(E10:H10) -> 629048
A11: 1405 | B11: Amortissements Incorporelles | C11: Actif | D11: Actif Non Courant | E11: =SUMIF(TB_Mere_IFRS!A:A, A11, TB_Mere_IFRS!E:E) -> 147337 | F11: =SUMIF(TB_FilialeA_IFRS!A:A, A11, TB_FilialeA_IFRS!E:E) -> 139130 | G11: =SUMIF(TB_FilialeB_IFRS!A:A, A11, TB_FilialeB_IFRS!E:E) -> 498570 | H11: 0 | I11: =SUM(E11:H11) -> 785037
A12: 1410 | B12: Goodwill | C12: Actif | D12: Actif Non Courant | E12: =SUMIF(TB_Mere_IFRS!A:A, A12, TB_Mere_IFRS!E:E) -> 485602 | F12: =SUMIF(TB_FilialeA_IFRS!A:A, A12, TB_FilialeA_IFRS!E:E) -> 56203 | G12: =SUMIF(TB_FilialeB_IFRS!A:A, A12, TB_FilialeB_IFRS!E:E) -> 481284 | H12: 0 | I12: =SUM(E12:H12) -> 1023089
A13: 1500 | B13: Actifs d'impôt différé | C13: Actif | D13: Actif Non Courant | E13: =SUMIF(TB_Mere_IFRS!A:A, A13, TB_Mere_IFRS!E:E) -> 440410 | F13: =SUMIF(TB_FilialeA_IFRS!A:A, A13, TB_FilialeA_IFRS!E:E) -> 230374 | G13: =SUMIF(TB_FilialeB_IFRS!A:A, A13, TB_FilialeB_IFRS!E:E) -> 185597 | H13: 0 | I13: =SUM(E13:H13) -> 856381
A14: 2000 | B14: Dettes Fournisseurs | C14: Passif | D14: Passif Courant | E14: =SUMIF(TB_Mere_IFRS!A:A, A14, TB_Mere_IFRS!E:E) -> -97498 | F14: =SUMIF(TB_FilialeA_IFRS!A:A, A14, TB_FilialeA_IFRS!E:E) -> -163313 | G14: =SUMIF(TB_FilialeB_IFRS!A:A, A14, TB_FilialeB_IFRS!E:E) -> -361292 | H14: 0 | I14: =SUM(E14:H14) -> -622103
A15: 2010 | B15: Dettes Inter-compagnies | C15: Passif | D15: Passif Courant | E15: =SUMIF(TB_Mere_IFRS!A:A, A15, TB_Mere_IFRS!E:E) -> -50000 | F15: =SUMIF(TB_FilialeA_IFRS!A:A, A15, TB_FilialeA_IFRS!E:E) -> -50000 | G15: =SUMIF(TB_FilialeB_IFRS!A:A, A15, TB_FilialeB_IFRS!E:E) -> -50000 | H15: =-(E15+F15+G15) -> 150000 | I15: =SUM(E15:H15) -> 0
A16: 2100 | B16: Dettes Financières Courantes | C16: Passif | D16: Passif Courant | E16: =SUMIF(TB_Mere_IFRS!A:A, A16, TB_Mere_IFRS!E:E) -> -398468 | F16: =SUMIF(TB_FilialeA_IFRS!A:A, A16, TB_FilialeA_IFRS!E:E) -> -458625 | G16: =SUMIF(TB_FilialeB_IFRS!A:A, A16, TB_FilialeB_IFRS!E:E) -> -371893 | H16: 0 | I16: =SUM(E16:H16) -> -1228986
A17: 2200 | B17: Provisions Courantes | C17: Passif | D17: Passif Courant | E17: =SUMIF(TB_Mere_IFRS!A:A, A17, TB_Mere_IFRS!E:E) -> -185203 | F17: =SUMIF(TB_FilialeA_IFRS!A:A, A17, TB_FilialeA_IFRS!E:E) -> -426382 | G17: =SUMIF(TB_FilialeB_IFRS!A:A, A17, TB_FilialeB_IFRS!E:E) -> -135148 | H17: 0 | I17: =SUM(E17:H17) -> -746733
A18: 2300 | B18: Dettes de Location Courantes (IFRS 16) | C18: Passif | D18: Passif Courant | E18: =SUMIF(TB_Mere_IFRS!A:A, A18, TB_Mere_IFRS!E:E) -> -201335 | F18: =SUMIF(TB_FilialeA_IFRS!A:A, A18, TB_FilialeA_IFRS!E:E) -> -259903 | G18: =SUMIF(TB_FilialeB_IFRS!A:A, A18, TB_FilialeB_IFRS!E:E) -> -331191 | H18: 0 | I18: =SUM(E18:H18) -> -792429
A19: 2400 | B19: Dettes Financières Non Courantes | C19: Passif | D19: Passif Non Courant | E19: =SUMIF(TB_Mere_IFRS!A:A, A19, TB_Mere_IFRS!E:E) -> -288167 | F19: =SUMIF(TB_FilialeA_IFRS!A:A, A19, TB_FilialeA_IFRS!E:E) -> -128857 | G19: =SUMIF(TB_FilialeB_IFRS!A:A, A19, TB_FilialeB_IFRS!E:E) -> -179425 | H19: 0 | I19: =SUM(E19:H19) -> -596449
A20: 2500 | B20: Passifs d'impôt différé | C20: Passif | D20: Passif Non Courant | E20: =SUMIF(TB_Mere_IFRS!A:A, A20, TB_Mere_IFRS!E:E) -> -51090 | F20: =SUMIF(TB_FilialeA_IFRS!A:A, A20, TB_FilialeA_IFRS!E:E) -> -81200 | G20: =SUMIF(TB_FilialeB_IFRS!A:A, A20, TB_FilialeB_IFRS!E:E) -> -108059 | H20: 0 | I20: =SUM(E20:H20) -> -240349
A21: 2600 | B21: Dettes de Location Non Courantes (IFRS 16) | C21: Passif | D21: Passif Non Courant | E21: =SUMIF(TB_Mere_IFRS!A:A, A21, TB_Mere_IFRS!E:E) -> -339365 | F21: =SUMIF(TB_FilialeA_IFRS!A:A, A21, TB_FilialeA_IFRS!E:E) -> -174782 | G21: =SUMIF(TB_FilialeB_IFRS!A:A, A21, TB_FilialeB_IFRS!E:E) -> -126200 | H21: 0 | I21: =SUM(E21:H21) -> -640347
A22: 3000 | B22: Capital Social | C22: Capitaux Propres | D22: Capitaux Propres | E22: =SUMIF(TB_Mere_IFRS!A:A, A22, TB_Mere_IFRS!E:E) -> -74820 | F22: =SUMIF(TB_FilialeA_IFRS!A:A, A22, TB_FilialeA_IFRS!E:E) -> -206719 | G22: =SUMIF(TB_FilialeB_IFRS!A:A, A22, TB_FilialeB_IFRS!E:E) -> -54787 | H22: 0 | I22: =SUM(E22:H22) -> -336326
A23: 3100 | B23: Réserves | C23: Capitaux Propres | D23: Capitaux Propres | E23: =SUMIF(TB_Mere_IFRS!A:A, A23, TB_Mere_IFRS!E:E) -> -272913 | F23: =SUMIF(TB_FilialeA_IFRS!A:A, A23, TB_FilialeA_IFRS!E:E) -> -242857 | G23: =SUMIF(TB_FilialeB_IFRS!A:A, A23, TB_FilialeB_IFRS!E:E) -> -491101 | H23: 0 | I23: =SUM(E23:H23) -> -1006871
A24: 3200 | B24: Résultat de l'exercice | C24: Capitaux Propres | D24: Capitaux Propres | E24: =SUMIF(TB_Mere_IFRS!A:A, A24, TB_Mere_IFRS!E:E) -> -2992116 | F24: =SUMIF(TB_FilialeA_IFRS!A:A, A24, TB_FilialeA_IFRS!E:E) -> -2507966 | G24: =SUMIF(TB_FilialeB_IFRS!A:A, A24, TB_FilialeB_IFRS!E:E) -> -2673249 | H24: 0 | I24: =SUM(E24:H24) -> -8173331
A25: 4000 | B25: Chiffre d'affaires | C25: Produit | D25: Produits d'exploitation | E25: =SUMIF(TB_Mere_IFRS!A:A, A25, TB_Mere_IFRS!E:E) -> -818315 | F25: =SUMIF(TB_FilialeA_IFRS!A:A, A25, TB_FilialeA_IFRS!E:E) -> -659950 | G25: =SUMIF(TB_FilialeB_IFRS!A:A, A25, TB_FilialeB_IFRS!E:E) -> -999042 | H25: 0 | I25: =SUM(E25:H25) -> -2477307
A26: 4100 | B26: Ventes Inter-compagnies | C26: Produit | D26: Produits d'exploitation | E26: =SUMIF(TB_Mere_IFRS!A:A, A26, TB_Mere_IFRS!E:E) -> -100000 | F26: =SUMIF(TB_FilialeA_IFRS!A:A, A26, TB_FilialeA_IFRS!E:E) -> -100000 | G26: =SUMIF(TB_FilialeB_IFRS!A:A, A26, TB_FilialeB_IFRS!E:E) -> -100000 | H26: =-(E26+F26+G26) -> 300000 | I26: =SUM(E26:H26) -> 0
A27: 5000 | B27: Coût des ventes | C27: Charge | D27: Charges d'exploitation | E27: =SUMIF(TB_Mere_IFRS!A:A, A27, TB_Mere_IFRS!E:E) -> 302709 | F27: =SUMIF(TB_FilialeA_IFRS!A:A, A27, TB_FilialeA_IFRS!E:E) -> 277748 | G27: =SUMIF(TB_FilialeB_IFRS!A:A, A27, TB_FilialeB_IFRS!E:E) -> 64420 | H27: 0 | I27: =SUM(E27:H27) -> 644877
A28: 5100 | B28: Achats Inter-compagnies | C28: Charge | D28: Charges d'exploitation | E28: =SUMIF(TB_Mere_IFRS!A:A, A28, TB_Mere_IFRS!E:E) -> 100000 | F28: =SUMIF(TB_FilialeA_IFRS!A:A, A28, TB_FilialeA_IFRS!E:E) -> 100000 | G28: =SUMIF(TB_FilialeB_IFRS!A:A, A28, TB_FilialeB_IFRS!E:E) -> 100000 | H28: =-(E28+F28+G28) -> -300000 | I28: =SUM(E28:H28) -> 0
A29: 5200 | B29: Frais de R&D | C29: Charge | D29: Charges d'exploitation | E29: =SUMIF(TB_Mere_IFRS!A:A, A29, TB_Mere_IFRS!E:E) -> 317455 | F29: =SUMIF(TB_FilialeA_IFRS!A:A, A29, TB_FilialeA_IFRS!E:E) -> 180256 | G29: =SUMIF(TB_FilialeB_IFRS!A:A, A29, TB_FilialeB_IFRS!E:E) -> 348859 | H29: 0 | I29: =SUM(E29:H29) -> 846570
A30: 5300 | B30: Amortissements PPE | C30: Charge | D30: Charges d'exploitation | E30: =SUMIF(TB_Mere_IFRS!A:A, A30, TB_Mere_IFRS!E:E) -> 153355 | F30: =SUMIF(TB_FilialeA_IFRS!A:A, A30, TB_FilialeA_IFRS!E:E) -> 395156 | G30: =SUMIF(TB_FilialeB_IFRS!A:A, A30, TB_FilialeB_IFRS!E:E) -> 124856 | H30: 0 | I30: =SUM(E30:H30) -> 673367
A31: 5310 | B31: Amortissement Droit d'utilisation | C31: Charge | D31: Charges d'exploitation | E31: =SUMIF(TB_Mere_IFRS!A:A, A31, TB_Mere_IFRS!E:E) -> 285796 | F31: =SUMIF(TB_FilialeA_IFRS!A:A, A31, TB_FilialeA_IFRS!E:E) -> 385665 | G31: =SUMIF(TB_FilialeB_IFRS!A:A, A31, TB_FilialeB_IFRS!E:E) -> 281940 | H31: 0 | I31: =SUM(E31:H31) -> 953401
A32: 5400 | B32: Charges de Personnel | C32: Charge | D32: Charges d'exploitation | E32: =SUMIF(TB_Mere_IFRS!A:A, A32, TB_Mere_IFRS!E:E) -> 264176 | F32: =SUMIF(TB_FilialeA_IFRS!A:A, A32, TB_FilialeA_IFRS!E:E) -> 357651 | G32: =SUMIF(TB_FilialeB_IFRS!A:A, A32, TB_FilialeB_IFRS!E:E) -> 458840 | H32: 0 | I32: =SUM(E32:H32) -> 1080667
A33: 5500 | B33: Frais de Marketing | C33: Charge | D33: Charges d'exploitation | E33: =SUMIF(TB_Mere_IFRS!A:A, A33, TB_Mere_IFRS!E:E) -> 234779 | F33: =SUMIF(TB_FilialeA_IFRS!A:A, A33, TB_FilialeA_IFRS!E:E) -> 207698 | G33: =SUMIF(TB_FilialeB_IFRS!A:A, A33, TB_FilialeB_IFRS!E:E) -> 277029 | H33: 0 | I33: =SUM(E33:H33) -> 719506
A34: 5600 | B34: Frais Administratifs | C34: Charge | D34: Charges d'exploitation | E34: =SUMIF(TB_Mere_IFRS!A:A, A34, TB_Mere_IFRS!E:E) -> 397449 | F34: =SUMIF(TB_FilialeA_IFRS!A:A, A34, TB_FilialeA_IFRS!E:E) -> 295799 | G34: =SUMIF(TB_FilialeB_IFRS!A:A, A34, TB_FilialeB_IFRS!E:E) -> 121998 | H34: 0 | I34: =SUM(E34:H34) -> 815246
A35: 6000 | B35: Charges Financières | C35: Charge | D35: Charges Financières | E35: =SUMIF(TB_Mere_IFRS!A:A, A35, TB_Mere_IFRS!E:E) -> 471909 | F35: =SUMIF(TB_FilialeA_IFRS!A:A, A35, TB_FilialeA_IFRS!E:E) -> 264338 | G35: =SUMIF(TB_FilialeB_IFRS!A:A, A35, TB_FilialeB_IFRS!E:E) -> 355510 | H35: 0 | I35: =SUM(E35:H35) -> 1091757
A36: 6010 | B36: Charges d'intérêts sur dettes de location | C36: Charge | D36: Charges Financières | E36: =SUMIF(TB_Mere_IFRS!A:A, A36, TB_Mere_IFRS!E:E) -> 308795 | F36: =SUMIF(TB_FilialeA_IFRS!A:A, A36, TB_FilialeA_IFRS!E:E) -> 433572 | G36: =SUMIF(TB_FilialeB_IFRS!A:A, A36, TB_FilialeB_IFRS!E:E) -> 416864 | H36: 0 | I36: =SUM(E36:H36) -> 1159231
A37: 7000 | B37: Impôts sur les bénéfices | C37: Charge | D37: Impôts | E37: =SUMIF(TB_Mere_IFRS!A:A, A37, TB_Mere_IFRS!E:E) -> 442752 | F37: =SUMIF(TB_FilialeA_IFRS!A:A, A37, TB_FilialeA_IFRS!E:E) -> 80255 | G37: =SUMIF(TB_FilialeB_IFRS!A:A, A37, TB_FilialeB_IFRS!E:E) -> 367993 | H37: 0 | I37: =SUM(E37:H37) -> 891000

Sheet Adj_US_GAAP
A1: ID_Ajustement | B1: ID_Compte | C1: Compte | D1: Debit | E1: Credit | F1: Description
A2: US_01 | B2: 5200 | C2: Frais de R&D | D2: 25000 | E2: 0 | F2: Expensing R&D capitalized under IFRS
A3: US_01 | B3: 1400 | C3: Immobilisations Incorporelles | D3: 0 | E3: 25000 | F3: Reversing capitalized R&D

Sheet Adj_UK_GAAP
A1: ID_Ajustement | B1: ID_Compte | C1: Compte | D1: Debit | E1: Credit | F1: Description
A2: UK_01 | B2: 5300 | C2: Amortissements PPE | D2: 10000 | E2: 0 | F2: Goodwill Amortization (10 years)
A3: UK_01 | B3: 1410 | C3: Goodwill | D3: 0 | E3: 10000 | F3: Accumulated Amortization Goodwill

Sheet Reconciliation_Bridge
A1: ID | B1: Compte | C1: IFRS_Consolide | D1: Adj_US_GAAP | E1: US_GAAP_Consolide | F1: Adj_UK_GAAP | G1: UK_GAAP_Consolide
A2: 1000 | B2: Trésorerie | C2: =Consolidation_IFRS!I2 -> 825135 | D2: =SUMIF(Adj_US_GAAP!B:B, A2, Adj_US_GAAP!D:D) - SUMIF(Adj_US_GAAP!B:B, A2, Adj_US_GAAP!E:E) -> 0 | E2: =C2 + D2 -> 825135 | F2: =SUMIF(Adj_UK_GAAP!B:B, A2, Adj_UK_GAAP!D:D) - SUMIF(Adj_UK_GAAP!B:B, A2, Adj_UK_GAAP!E:E) -> 0 | G2: =C2 + F2 -> 825135
A3: 1100 | B3: Créances Clients | C3: =Consolidation_IFRS!I3 -> 520885 | D3: =SUMIF(Adj_US_GAAP!B:B, A3, Adj_US_GAAP!D:D) - SUMIF(Adj_US_GAAP!B:B, A3, Adj_US_GAAP!E:E) -> 0 | E3: =C3 + D3 -> 520885 | F3: =SUMIF(Adj_UK_GAAP!B:B, A3, Adj_UK_GAAP!D:D) - SUMIF(Adj_UK_GAAP!B:B, A3, Adj_UK_GAAP!E:E) -> 0 | G3: =C3 + F3 -> 520885
A4: 1110 | B4: Créances Inter-compagnies | C4: =Consolidation_IFRS!I4 -> 0 | D4: =SUMIF(Adj_US_GAAP!B:B, A4, Adj_US_GAAP!D:D) - SUMIF(Adj_US_GAAP!B:B, A4, Adj_US_GAAP!E:E) -> 0 | E4: =C4 + D4 -> 0 | F4: =SUMIF(Adj_UK_GAAP!B:B, A4, Adj_UK_GAAP!D:D) - SUMIF(Adj_UK_GAAP!B:B, A4, Adj_UK_GAAP!E:E) -> 0 | G4: =C4 + F4 -> 0
A5: 1200 | B5: Stocks | C5: =Consolidation_IFRS!I5 -> 637401 | D5: =SUMIF(Adj_US_GAAP!B:B, A5, Adj_US_GAAP!D:D) - SUMIF(Adj_US_GAAP!B:B, A5, Adj_US_GAAP!E:E) -> 0 | E5: =C5 + D5 -> 637401 | F5: =SUMIF(Adj_UK_GAAP!B:B, A5, Adj_UK_GAAP!D:D) - SUMIF(Adj_UK_GAAP!B:B, A5, Adj_UK_GAAP!E:E) -> 0 | G5: =C5 + F5 -> 637401
A6: 1300 | B6: Immobilisations Corporelles (PPE) | C6: =Consolidation_IFRS!I6 -> 799136 | D6: =SUMIF(Adj_US_GAAP!B:B, A6, Adj_US_GAAP!D:D) - SUMIF(Adj_US_GAAP!B:B, A6, Adj_US_GAAP!E:E) -> 0 | E6: =C6 + D6 -> 799136 | F6: =SUMIF(Adj_UK_GAAP!B:B, A6, Adj_UK_GAAP!D:D) - SUMIF(Adj_UK_GAAP!B:B, A6, Adj_UK_GAAP!E:E) -> 0 | G6: =C6 + F6 -> 799136
A7: 1305 | B7: Amortissements PPE | C7: =Consolidation_IFRS!I7 -> 935880 | D7: =SUMIF(Adj_US_GAAP!B:B, A7, Adj_US_GAAP!D:D) - SUMIF(Adj_US_GAAP!B:B, A7, Adj_US_GAAP!E:E) -> 0 | E7: =C7 + D7 -> 935880 | F7: =SUMIF(Adj_UK_GAAP!B:B, A7, Adj_UK_GAAP!D:D) - SUMIF(Adj_UK_GAAP!B:B, A7, Adj_UK_GAAP!E:E) -> 0 | G7: =C7 + F7 -> 935880
A8: 1310 | B8: Droit d'utilisation (IFRS 16) | C8: =Consolidation_IFRS!I8 -> 556654 | D8: =SUMIF(Adj_US_GAAP!B:B, A8, Adj_US_GAAP!D:D) - SUMIF(Adj_US_GAAP!B:B, A8, Adj_US_GAAP!E:E) -> 0 | E8: =C8 + D8 -> 556654 | F8: =SUMIF(Adj_UK_GAAP!B:B, A8, Adj_UK_GAAP!D:D) - SUMIF(Adj_UK_GAAP!B:B, A8, Adj_UK_GAAP!E:E) -> 0 | G8: =C8 + F8 -> 556654
A9: 1315 | B9: Amortissement Droit d'utilisation | C9: =Consolidation_IFRS!I9 -> 416963 | D9: =SUMIF(Adj_US_GAAP!B:B, A9, Adj_US_GAAP!D:D) - SUMIF(Adj_US_GAAP!B:B, A9, Adj_US_GAAP!E:E) -> 0 | E9: =C9 + D9 -> 416963 | F9: =SUMIF(Adj_UK_GAAP!B:B, A9, Adj_UK_GAAP!D:D) - SUMIF(Adj_UK_GAAP!B:B, A9, Adj_UK_GAAP!E:E) -> 0 | G9: =C9 + F9 -> 416963
A10: 1400 | B10: Immobilisations Incorporelles | C10: =Consolidation_IFRS!I10 -> 629048 | D10: =SUMIF(Adj_US_GAAP!B:B, A10, Adj_US_GAAP!D:D) - SUMIF(Adj_US_GAAP!B:B, A10, Adj_US_GAAP!E:E) -> -25000 | E10: =C10 + D10 -> 604048 | F10: =SUMIF(Adj_UK_GAAP!B:B, A10, Adj_UK_GAAP!D:D) - SUMIF(Adj_UK_GAAP!B:B, A10, Adj_UK_GAAP!E:E) -> 0 | G10: =C10 + F10 -> 629048
A11: 1405 | B11: Amortissements Incorporelles | C11: =Consolidation_IFRS!I11 -> 785037 | D11: =SUMIF(Adj_US_GAAP!B:B, A11, Adj_US_GAAP!D:D) - SUMIF(Adj_US_GAAP!B:B, A11, Adj_US_GAAP!E:E) -> 0 | E11: =C11 + D11 -> 785037 | F11: =SUMIF(Adj_UK_GAAP!B:B, A11, Adj_UK_GAAP!D:D) - SUMIF(Adj_UK_GAAP!B:B, A11, Adj_UK_GAAP!E:E) -> 0 | G11: =C11 + F11 -> 785037
A12: 1410 | B12: Goodwill | C12: =Consolidation_IFRS!I12 -> 1023089 | D12: =SUMIF(Adj_US_GAAP!B:B, A12, Adj_US_GAAP!D:D) - SUMIF(Adj_US_GAAP!B:B, A12, Adj_US_GAAP!E:E) -> 0 | E12: =C12 + D12 -> 1023089 | F12: =SUMIF(Adj_UK_GAAP!B:B, A12, Adj_UK_GAAP!D:D) - SUMIF(Adj_UK_GAAP!B:B, A12, Adj_UK_GAAP!E:E) -> -10000 | G12: =C12 + F12 -> 1013089
A13: 1500 | B13: Actifs d'impôt différé | C13: =Consolidation_IFRS!I13 -> 856381 | D13: =SUMIF(Adj_US_GAAP!B:B, A13, Adj_US_GAAP!D:D) - SUMIF(Adj_US_GAAP!B:B, A13, Adj_US_GAAP!E:E) -> 0 | E13: =C13 + D13 -> 856381 | F13: =SUMIF(Adj_UK_GAAP!B:B, A13, Adj_UK_GAAP!D:D) - SUMIF(Adj_UK_GAAP!B:B, A13, Adj_UK_GAAP!E:E) -> 0 | G13: =C13 + F13 -> 856381
... A37: 7000 | B37: Impôts sur les bénéfices | C37: =Consolidation_IFRS!I37 -> 891000 | D37: =SUMIF(Adj_US_GAAP!B:B, A37, Adj_US_GAAP!D:D) - SUMIF(Adj_US_GAAP!B:B, A37, Adj_US_GAAP!E:E) -> 0 | E37: =C37 + D37 -> 891000 | F37: =SUMIF(Adj_UK_GAAP!B:B, A37, Adj_UK_GAAP!D:D) - SUMIF(Adj_UK_GAAP!B:B, A37, Adj_UK_GAAP!E:E) -> 0 | G37: =C37 + F37 -> 891000

Sheet Financial_Statements
A1: ETATS FINANCIERS CONSOLIDES COMPARATIFS | C1: IFRS | D1: US GAAP | E1: UK GAAP
A3: COMPTE DE RESULTAT
A4: Chiffre d'affaires | B4: 4000 | C4: =SUMIF(Reconciliation_Bridge!A:A, B4, Reconciliation_Bridge!C:C) -> -2477307 | D4: =SUMIF(Reconciliation_Bridge!A:A, B4, Reconciliation_Bridge!E:E) -> -2477307 | E4: =SUMIF(Reconciliation_Bridge!A:A, B4, Reconciliation_Bridge!G:G) -> -2477307
A5: Coût des ventes | B5: 5000 | C5: =SUMIF(Reconciliation_Bridge!A:A, B5, Reconciliation_Bridge!C:C) -> 644877 | D5: =SUMIF(Reconciliation_Bridge!A:A, B5, Reconciliation_Bridge!E:E) -> 644877 | E5: =SUMIF(Reconciliation_Bridge!A:A, B5, Reconciliation_Bridge!G:G) -> 644877
A6: Frais de R&D | B6: 5200 | C6: =SUMIF(Reconciliation_Bridge!A:A, B6, Reconciliation_Bridge!C:C) -> 846570 | D6: =SUMIF(Reconciliation_Bridge!A:A, B6, Reconciliation_Bridge!E:E) -> 871570 | E6: =SUMIF(Reconciliation_Bridge!A:A, B6, Reconciliation_Bridge!G:G) -> 846570
A7: Charges de Personnel | B7: 5400 | C7: =SUMIF(Reconciliation_Bridge!A:A, B7, Reconciliation_Bridge!C:C) -> 1080667 | D7: =SUMIF(Reconciliation_Bridge!A:A, B7, Reconciliation_Bridge!E:E) -> 1080667 | E7: =SUMIF(Reconciliation_Bridge!A:A, B7, Reconciliation_Bridge!G:G) -> 1080667
A8: Frais de Marketing | B8: 5500 | C8: =SUMIF(Reconciliation_Bridge!A:A, B8, Reconciliation_Bridge!C:C) -> 719506 | D8: =SUMIF(Reconciliation_Bridge!A:A, B8, Reconciliation_Bridge!E:E) -> 719506 | E8: =SUMIF(Reconciliation_Bridge!A:A, B8, Reconciliation_Bridge!G:G) -> 719506
A9: Frais Administratifs | B9: 5600 | C9: =SUMIF(Reconciliation_Bridge!A:A, B9, Reconciliation_Bridge!C:C) -> 815246 | D9: =SUMIF(Reconciliation_Bridge!A:A, B9, Reconciliation_Bridge!E:E) -> 815246 | E9: =SUMIF(Reconciliation_Bridge!A:A, B9, Reconciliation_Bridge!G:G) -> 815246
A10: Amortissements | B10: 5300 | C10: =SUMIF(Reconciliation_Bridge!A:A, B10, Reconciliation_Bridge!C:C) -> 673367 | D10: =SUMIF(Reconciliation_Bridge!A:A, B10, Reconciliation_Bridge!E:E) -> 673367 | E10: =SUMIF(Reconciliation_Bridge!A:A, B10, Reconciliation_Bridge!G:G) -> 683367
A11: Charges Financières | B11: 6000 | C11: =SUMIF(Reconciliation_Bridge!A:A, B11, Reconciliation_Bridge!C:C) -> 1091757 | D11: =SUMIF(Reconciliation_Bridge!A:A, B11, Reconciliation_Bridge!E:E) -> 1091757 | E11: =SUMIF(Reconciliation_Bridge!A:A, B11, Reconciliation_Bridge!G:G) -> 1091757
A12: Impôts sur les bénéfices | B12: 7000 | C12: =SUMIF(Reconciliation_Bridge!A:A, B12, Reconciliation_Bridge!C:C) -> 891000 | D12: =SUMIF(Reconciliation_Bridge!A:A, B12, Reconciliation_Bridge!E:E) -> 891000 | E12: =SUMIF(Reconciliation_Bridge!A:A, B12, Reconciliation_Bridge!G:G) -> 891000
A13: RESULTAT NET | C13: =SUM(C4:C12) -> 4285683 | D13: =SUM(D4:D12) -> 4310683 | E13: =SUM(E4:E12) -> 4295683
A15: BILAN CONSOLIDE
A16: Trésorerie | B16: 1000 | C16: =SUMIF(Reconciliation_Bridge!A:A, B16, Reconciliation_Bridge!C:C) -> 825135 | D16: =SUMIF(Reconciliation_Bridge!A:A, B16, Reconciliation_Bridge!E:E) -> 825135 | E16: =SUMIF(Reconciliation_Bridge!A:A, B16, Reconciliation_Bridge!G:G) -> 825135
A17: Créances Clients | B17: 1100 | C17: =SUMIF(Reconciliation_Bridge!A:A, B17, Reconciliation_Bridge!C:C) -> 520885 | D17: =SUMIF(Reconciliation_Bridge!A:A, B17, Reconciliation_Bridge!E:E) -> 520885 | E17: =SUMIF(Reconciliation_Bridge!A:A, B17, Reconciliation_Bridge!G:G) -> 520885
A18: Stocks | B18: 1200 | C18: =SUMIF(Reconciliation_Bridge!A:A, B18, Reconciliation_Bridge!C:C) -> 637401 | D18: =SUMIF(Reconciliation_Bridge!A:A, B18, Reconciliation_Bridge!E:E) -> 637401 | E18: =SUMIF(Reconciliation_Bridge!A:A, B18, Reconciliation_Bridge!G:G) -> 637401
A19: Immobilisations Corporelles | B19: 1300 | C19: =SUMIF(Reconciliation_Bridge!A:A, B19, Reconciliation_Bridge!C:C) -> 799136 | D19: =SUMIF(Reconciliation_Bridge!A:A, B19, Reconciliation_Bridge!E:E) -> 799136 | E19: =SUMIF(Reconciliation_Bridge!A:A, B19, Reconciliation_Bridge!G:G) -> 799136
A20: Immobilisations Incorporelles | B20: 1400 | C20: =SUMIF(Reconciliation_Bridge!A:A, B20, Reconciliation_Bridge!C:C) -> 629048 | D20: =SUMIF(Reconciliation_Bridge!A:A, B20, Reconciliation_Bridge!E:E) -> 604048 | E20: =SUMIF(Reconciliation_Bridge!A:A, B20, Reconciliation_Bridge!G:G) -> 629048
A21: Goodwill | B21: 1410 | C21: =SUMIF(Reconciliation_Bridge!A:A, B21, Reconciliation_Bridge!C:C) -> 1023089 | D21: =SUMIF(Reconciliation_Bridge!A:A, B21, Reconciliation_Bridge!E:E) -> 1023089 | E21: =SUMIF(Reconciliation_Bridge!A:A, B21, Reconciliation_Bridge!G:G) -> 1013089
A22: Dettes Fournisseurs | B22: 2000 | C22: =SUMIF(Reconciliation_Bridge!A:A, B22, Reconciliation_Bridge!C:C) -> -622103 | D22: =SUMIF(Reconciliation_Bridge!A:A, B22, Reconciliation_Bridge!E:E) -> -622103 | E22: =SUMIF(Reconciliation_Bridge!A:A, B22, Reconciliation_Bridge!G:G) -> -622103
A23: Dettes Financières | B23: 2100 | C23: =SUMIF(Reconciliation_Bridge!A:A, B23, Reconciliation_Bridge!C:C) -> -1228986 | D23: =SUMIF(Reconciliation_Bridge!A:A, B23, Reconciliation_Bridge!E:E) -> -1228986 | E23: =SUMIF(Reconciliation_Bridge!A:A, B23, Reconciliation_Bridge!G:G) -> -1228986
A24: Capital Social | B24: 3000 | C24: =SUMIF(Reconciliation_Bridge!A:A, B24, Reconciliation_Bridge!C:C) -> -336326 | D24: =SUMIF(Reconciliation_Bridge!A:A, B24, Reconciliation_Bridge!E:E) -> -336326 | E24: =SUMIF(Reconciliation_Bridge!A:A, B24, Reconciliation_Bridge!G:G) -> -336326
A25: Réserves | B25: 3100 | C25: =SUMIF(Reconciliation_Bridge!A:A, B25, Reconciliation_Bridge!C:C) -> -1006871 | D25: =SUMIF(Reconciliation_Bridge!A:A, B25, Reconciliation_Bridge!E:E) -> -1006871 | E25: =SUMIF(Reconciliation_Bridge!A:A, B25, Reconciliation_Bridge!G:G) -> -1006871

Sheet Documentation_Technique
A1: PROJET : AUTOMATISATION REPORTING MULTI-NORMES
A3: 1. METHODOLOGIE DE CONSOLIDATION
A4: - Agrégation des Balances de Vérification (TB) des 3 entités via SUMIF.
A5: - Élimination automatique des flux inter-compagnies (comptes 1110, 2010, 4100, 5100).
A7: 2. LOGIQUE DE RECONCILIATION (BRIDGE)
A8: - IFRS -> US GAAP : Retraitement des frais de R&D capitalisés (IAS 38 vs ASC 730).
A9: - IFRS -> UK GAAP : Amortissement systématique du Goodwill (FRS 102).
A11: 3. FORMULES CLES UTILISEES
A12: - SUMIF / SOMME.SI : Pour l'agrégation dynamique des comptes.
A13: - Formules de liaison inter-feuilles pour garantir l'intégrité des données.
A14: - Tests de cohérence (Bilan équilibré) intégrés dans les états financiers.
