Workbook

Sheet Hypothèses
A1: Taux de marché
A2: Taux de base (EURIBOR 3m) | B2: 0.0203 | D2: Situation de l'entreprise (contexte du modèle) Le modèle que nous avons construit simule la structure financière d’une entreprise française industrielle réalisant un chiffre d’affaires stable et disposant d’un EBITDA de 30 M€ en 2026, avec une croissance annuelle de 5 %. Cette société est financée par une combinaison de dettes dans le cadre d’une opération typique de LBO (acquisition par effet de levier). Elle présente un besoin de financement total de 250 M€ réparti comme suit : Dette senior : 100 M€ (taux EURIBOR + 2 %) Term Loan B : 75 M€ (taux EURIBOR + 4 %, amortissement 1 % par an) Dette mezzanine : 50 M€ (taux cash 7 % + PIK 2 %) Ligne de crédit renouvelable : 25 M€ (plafond, taux EURIBOR + 2,5 %)
A4: Crédit Renouvelable (Revolver)
A5: Plafond (montant max) | B5: 25000000
A6: Marge | B6: 0.025
A7: Taux débiteur | B7: =B2+B6 -> 0.0453
A8: Commission de non-utilisation | B8: 0.0035
A10: Dette Senior
A11: Montant emprunté | B11: 100000000
A12: Marge | B12: 0.02
A13: Taux débiteur | B13: =B2+B12 -> 0.0403
A14: Durée (ans) | B14: 7
A16: Term Loan B
A17: Montant emprunté | B17: 75000000
A18: Marge | B18: 0.04
A19: Taux débiteur | B19: =B2+B18 -> 0.0603
A20: Durée (ans) | B20: 7
A21: Amortissement annuel (% du montant initial) | B21: 0.01
A22: Frais d'émission (OID) | B22: 0.015
A24: Dette Mezzanine
A25: Montant emprunté | B25: 50000000
A26: Taux d'intérêt cash | B26: 0.07
A27: Taux d'intérêt PIK | B27: 0.02
A28: Taux global | B28: =B26+B27 -> 0.09
A29: Durée (ans) | B29: 7
A30: Frais de mise en place | B30: 0.01
A32: Paramètres généraux
A33: Taux de sweep (remboursement anticipé) | B33: 0.03
A34: Réserve de trésorerie obligatoire (annuelle) | B34: 100000

Sheet Ligne de crédit
C1: SUIVI DU CRÉDIT RENOUVELABLE (REVOLVER)
B5: {=_xlfn.SEQUENCE(1,7,2026,1)} -> 2026 | C5: 2027 | D5: 2028 | E5: 2029 | F5: 2030 | G5: 2031 | H5: 2032
A6: Solde début | B6: 5000000 | C6: =B8 -> 8435714.3 | D6: =C8 -> 9171428.6 | E6: =D8 -> 9106500 | F6: =E8 -> 8891590.7 | G6: =F8 -> 8444200.1 | H6: =G8 -> 7684302.7
A7: Tirage (+) / Remboursement (-) de l'année | B7: ='Flux de trésorerie'!B13+'Flux de trésorerie'!B14 -> 3435714.3 | C7: ='Flux de trésorerie'!C13+'Flux de trésorerie'!C14 -> 735714.29 | D7: ='Flux de trésorerie'!D13+'Flux de trésorerie'!D14 -> -64928.571 | E7: ='Flux de trésorerie'!E13+'Flux de trésorerie'!E14 -> -214909.29 | F7: ='Flux de trésorerie'!F13+'Flux de trésorerie'!F14 -> -447390.58 | G7: ='Flux de trésorerie'!G13+'Flux de trésorerie'!G14 -> -759897.43 | H7: ='Flux de trésorerie'!H13+'Flux de trésorerie'!H14 -> 28999981
A8: Solde fin | B8: =B6+B7 -> 8435714.3 | C8: =C6+C7 -> 9171428.6 | D8: =D6+D7 -> 9106500 | E8: =E6+E7 -> 8891590.7 | F8: =F6+F7 -> 8444200.1 | G8: =G6+G7 -> 7684302.7 | H8: =H6+H7 -> 36684283
A9: Capacité totale (plafond) | B9: =Hypothèses!$B$5 -> 25000000 | C9: =Hypothèses!$B$5 -> 25000000 | D9: =Hypothèses!$B$5 -> 25000000 | E9: =Hypothèses!$B$5 -> 25000000 | F9: =Hypothèses!$B$5 -> 25000000 | G9: =Hypothèses!$B$5 -> 25000000 | H9: =Hypothèses!$B$5 -> 25000000
A10: Part non utilisée | B10: =B9-B8 -> 16564286 | C10: =C9-C8 -> 15828571 | D10: =D9-D8 -> 15893500 | E10: =E9-E8 -> 16108409 | F10: =F9-F8 -> 16555800 | G10: =G9-G8 -> 17315697 | H10: =H9-H8 -> -11684283
A11: Commission de non-utilisation | B11: =B10*Hypothèses!$B$8 -> 57975 | C11: =C10*Hypothèses!$B$8 -> 55400 | D11: =D10*Hypothèses!$B$8 -> 55627.25 | E11: =E10*Hypothèses!$B$8 -> 56379.433 | F11: =F10*Hypothèses!$B$8 -> 57945.3 | G11: =G10*Hypothèses!$B$8 -> 60604.941 | H11: =H10*Hypothèses!$B$8 -> -40894.992
A12: Intérêts payés | B12: =B8*Hypothèses!$B$7 -> 382137.86 | C12: =C8*Hypothèses!$B$7 -> 415465.71 | D12: =D8*Hypothèses!$B$7 -> 412524.45 | E12: =E8*Hypothèses!$B$7 -> 402789.06 | F12: =F8*Hypothèses!$B$7 -> 382522.27 | G12: =G8*Hypothèses!$B$7 -> 348098.91 | H12: =H8*Hypothèses!$B$7 -> 1661798

Sheet Dette Mezzanine
C1: DETTE MEZZANINE - Financement hybride avec intérêts capitalisés
A5: Année | B5: {=_xlfn.SEQUENCE(1,7,2026,1)} -> 2026 | C5: 2027 | D5: 2028 | E5: 2029 | F5: 2030 | G5: 2031 | H5: 2032
A6: Solde début | B6: =Hypothèses!B25 -> 50000000 | C6: =B11 -> 51000000 | D6: =C11 -> 52020000 | E6: =D11 -> 53060400 | F6: =E11 -> 54121608 | G6: =F11 -> 55204040 | H6: =G11 -> 56308121
A7: Intérêts cash (payés) | B7: =B6*Hypothèses!$B$26 -> 3500000 | C7: =C6*Hypothèses!$B$26 -> 3570000 | D7: =D6*Hypothèses!$B$26 -> 3641400 | E7: =E6*Hypothèses!$B$26 -> 3714228 | F7: =F6*Hypothèses!$B$26 -> 3788512.6 | G7: =G6*Hypothèses!$B$26 -> 3864282.8 | H7: =H6*Hypothèses!$B$26 -> 3941568.5
A8: Intérêts PIK (capitalisés) | B8: =B6*Hypothèses!$B$27 -> 1000000 | C8: =C6*Hypothèses!$B$27 -> 1020000 | D8: =D6*Hypothèses!$B$27 -> 1040400 | E8: =E6*Hypothèses!$B$27 -> 1061208 | F8: =F6*Hypothèses!$B$27 -> 1082432.2 | G8: =G6*Hypothèses!$B$27 -> 1104080.8 | H8: =H6*Hypothèses!$B$27 -> 1126162.4
A9: Remboursement anticipé | B9: 0 | C9: 0 | D9: 0 | E9: 0 | F9: 0 | G9: 0 | H9: 0
A10: Remboursement in fine (dernière année) | B10: 0 | C10: 0 | D10: 0 | E10: 0 | F10: 0 | G10: 0 | H10: =H6+H8 -> 57434283
A11: Solde fin | B11: =B6+B8+B9-B10 -> 51000000 | C11: =C6+C8+C9-C10 -> 52020000 | D11: =D6+D8+D9-D10 -> 53060400 | E11: =E6+E8+E9-E10 -> 54121608 | F11: =F6+F8+F9-F10 -> 55204040 | G11: =G6+G8+G9-G10 -> 56308121 | H11: =H6+H8+H9-H10 -> 0
A12: Total cash sorti (intérêts cash + remboursements) | B12: =B7+B9+B10 -> 3500000 | C12: =C7+C9+C10 -> 3570000 | D12: =D7+D9+D10 -> 3641400 | E12: =E7+E9+E10 -> 3714228 | F12: =F7+F9+F10 -> 3788512.6 | G12: =G7+G9+G10 -> 3864282.8 | H12: =H7+H9+H10 -> 61375852

Sheet Prêt Terme B
C1: TERM LOAN B - Dette avec amortissement minimal (1% par an)
A5: Année | B5: {=_xlfn.SEQUENCE(1,7,2026,1)} -> 2026 | C5: 2027 | D5: 2028 | E5: 2029 | F5: 2030 | G5: 2031 | H5: 2032
A6: Solde début | B6: =Hypothèses!B17 -> 75000000 | C6: =B10 -> 74250000 | D6: =C10 -> 73500000 | E6: =D10 -> 72750000 | F6: =E10 -> 72000000 | G6: =F10 -> 71250000 | H6: =G10 -> 70500000
A7: Amortissement obligatoire (1%) | B7: =Hypothèses!$B$17*Hypothèses!$B$21 -> 750000 | C7: =Hypothèses!$B$17*Hypothèses!$B$21 -> 750000 | D7: =Hypothèses!$B$17*Hypothèses!$B$21 -> 750000 | E7: =Hypothèses!$B$17*Hypothèses!$B$21 -> 750000 | F7: =Hypothèses!$B$17*Hypothèses!$B$21 -> 750000 | G7: =Hypothèses!$B$17*Hypothèses!$B$21 -> 750000 | H7: =Hypothèses!$B$17*Hypothèses!$B$21 -> 750000
A8: Remboursement anticipé | B8: 0 | C8: 0 | D8: 0 | E8: 0 | F8: 0 | G8: 0 | H8: 0
A9: Remboursement in fine (dernière année) | B9: 0 | C9: 0 | D9: 0 | E9: 0 | F9: 0 | G9: 0 | H9: =H6-H7 -> 69750000
A10: Solde fin | B10: =B6-B7-B8-B9 -> 74250000 | C10: =C6-C7 -> 73500000 | D10: =D6-D7 -> 72750000 | E10: =E6-E7 -> 72000000 | F10: =F6-F7 -> 71250000 | G10: =G6-G7 -> 70500000 | H10: =H6-H7-H8-H9 -> 0
A11: Intérêts | B11: =B6*Hypothèses!$B$19 -> 4522500 | C11: =C6*Hypothèses!$B$19 -> 4477275 | D11: =D6*Hypothèses!$B$19 -> 4432050 | E11: =E6*Hypothèses!$B$19 -> 4386825 | F11: =F6*Hypothèses!$B$19 -> 4341600 | G11: =G6*Hypothèses!$B$19 -> 4296375 | H11: =H6*Hypothèses!$B$19 -> 4251150
A12: Total cash sorti | B12: =B7+B8+B9+B11 -> 5272500 | C12: =C7+C8+C9+C11 -> 5227275 | D12: =D7+D8+D9+D11 -> 5182050 | E12: =E7+E8+E9+E11 -> 5136825 | F12: =F7+F8+F9+F11 -> 5091600 | G12: =G7+G8+G9+G11 -> 5046375 | H12: =H7+H8+H9+H11 -> 74751150

Sheet Dette senior
C2: DETTE SENIOR - Financement bancaire classique amortissable
A5: Année | B5: {=_xlfn.SEQUENCE(1,7,2026,1)} -> 2026 | C5: 2027 | D5: 2028 | E5: 2029 | F5: 2030 | G5: 2031 | H5: 2032
A6: Solde début | B6: =Hypothèses!$B$11 -> 100000000 | C6: =B8 -> 85714286 | D6: =C8 -> 71428571 | E6: =D8 -> 57142857 | F6: =E8 -> 42857143 | G6: =F8 -> 28571429 | H6: =G8 -> 14285714
A7: Remboursement (amortissement) | B7: =Hypothèses!$B$11/Hypothèses!$B$14 -> 14285714 | C7: =Hypothèses!$B$11/Hypothèses!$B$14 -> 14285714 | D7: =Hypothèses!$B$11/Hypothèses!$B$14 -> 14285714 | E7: =Hypothèses!$B$11/Hypothèses!$B$14 -> 14285714 | F7: =Hypothèses!$B$11/Hypothèses!$B$14 -> 14285714 | G7: =Hypothèses!$B$11/Hypothèses!$B$14 -> 14285714 | H7: =Hypothèses!$B$11/Hypothèses!$B$14 -> 14285714
A8: Solde fin | B8: =B6-B7 -> 85714286 | C8: =C6-C7 -> 71428571 | D8: =D6-D7 -> 57142857 | E8: =E6-E7 -> 42857143 | F8: =F6-F7 -> 28571429 | G8: =G6-G7 -> 14285714 | H8: =H6-H7 -> 0
A9: Intérêts | B9: =B6*Hypothèses!$B$13 -> 4030000 | C9: =C6*Hypothèses!$B$13 -> 3454285.7 | D9: =D6*Hypothèses!$B$13 -> 2878571.4 | E9: =E6*Hypothèses!$B$13 -> 2302857.1 | F9: =F6*Hypothèses!$B$13 -> 1727142.9 | G9: =G6*Hypothèses!$B$13 -> 1151428.6 | H9: =H6*Hypothèses!$B$13 -> 575714.29
A10: Total cash sorti (intérêts + remboursement) | B10: =B9+B7 -> 18315714 | C10: =C9+C7 -> 17740000 | D10: =D9+D7 -> 17164286 | E10: =E9+E7 -> 16588571 | F10: =F9+F7 -> 16012857 | G10: =G9+G7 -> 15437143 | H10: =H9+H7 -> 14861429

Sheet Dette consolidée
C1: CASCADE DE TRÉSORERIE - Détermine les capacités de remboursement
A6: Soldes de dettes (fin d'année) | B6: {=_xlfn.SEQUENCE(1,7,2026,1)} -> 2026 | C6: 2027 | D6: 2028 | E6: 2029 | F6: 2030 | G6: 2031 | H6: 2032
A7: Ligne de crédit | B7: ='Ligne de crédit'!B8 -> 8435714.3 | C7: ='Ligne de crédit'!C8 -> 9171428.6 | D7: ='Ligne de crédit'!D8 -> 9106500 | E7: ='Ligne de crédit'!E8 -> 8891590.7 | F7: ='Ligne de crédit'!F8 -> 8444200.1 | G7: ='Ligne de crédit'!G8 -> 7684302.7 | H7: ='Ligne de crédit'!H8 -> 36684283
A8: Dette senior | B8: ='Dette senior'!B8 -> 85714286 | C8: ='Dette senior'!C8 -> 71428571 | D8: ='Dette senior'!D8 -> 57142857 | E8: ='Dette senior'!E8 -> 42857143 | F8: ='Dette senior'!F8 -> 28571429 | G8: ='Dette senior'!G8 -> 14285714 | H8: ='Dette senior'!H8 -> 0
A9: Dette mezzanine | B9: ='Dette Mezzanine'!B11 -> 51000000 | C9: ='Dette Mezzanine'!C11 -> 52020000 | D9: ='Dette Mezzanine'!D11 -> 53060400 | E9: ='Dette Mezzanine'!E11 -> 54121608 | F9: ='Dette Mezzanine'!F11 -> 55204040 | G9: ='Dette Mezzanine'!G11 -> 56308121 | H9: ='Dette Mezzanine'!H11 -> 0
A10: Term Loan B | B10: ='Prêt Terme B'!B10 -> 74250000 | C10: ='Prêt Terme B'!C10 -> 73500000 | D10: ='Prêt Terme B'!D10 -> 72750000 | E10: ='Prêt Terme B'!E10 -> 72000000 | F10: ='Prêt Terme B'!F10 -> 71250000 | G10: ='Prêt Terme B'!G10 -> 70500000 | H10: ='Prêt Terme B'!H10 -> 0
A11: Dette totale | B11: =SUM(B7:B10) -> 219400000 | C11: =SUM(C7:C10) -> 206120000 | D11: =SUM(D7:D10) -> 1.9205976e+08 | E11: =SUM(E7:E10) -> 1.7787034e+08 | F11: =SUM(F7:F10) -> 1.6346967e+08 | G11: =SUM(G7:G10) -> 1.4877814e+08 | H11: =SUM(H7:H10) -> 36684283
A13: Intérêts cash
A14: Ligne de crédit | B14: ='Ligne de crédit'!B12 -> 382137.86 | C14: ='Ligne de crédit'!C12 -> 415465.71 | D14: ='Ligne de crédit'!D12 -> 412524.45 | E14: ='Ligne de crédit'!E12 -> 402789.06 | F14: ='Ligne de crédit'!F12 -> 382522.27 | G14: ='Ligne de crédit'!G12 -> 348098.91 | H14: ='Ligne de crédit'!H12 -> 1661798
A15: Dette senior | B15: ='Dette senior'!B9 -> 4030000 | C15: ='Dette senior'!C9 -> 3454285.7 | D15: ='Dette senior'!D9 -> 2878571.4 | E15: ='Dette senior'!E9 -> 2302857.1 | F15: ='Dette senior'!F9 -> 1727142.9 | G15: ='Dette senior'!G9 -> 1151428.6 | H15: ='Dette senior'!H9 -> 575714.29
A16: Dette mezzanine (cash) | B16: ='Dette Mezzanine'!B7 -> 3500000 | C16: ='Dette Mezzanine'!C7 -> 3570000 | D16: ='Dette Mezzanine'!D7 -> 3641400 | E16: ='Dette Mezzanine'!E7 -> 3714228 | F16: ='Dette Mezzanine'!F7 -> 3788512.6 | G16: ='Dette Mezzanine'!G7 -> 3864282.8 | H16: ='Dette Mezzanine'!H7 -> 3941568.5
A17: Term Loan B | B17: ='Prêt Terme B'!B11 -> 4522500 | C17: ='Prêt Terme B'!C11 -> 4477275 | D17: ='Prêt Terme B'!D11 -> 4432050 | E17: ='Prêt Terme B'!E11 -> 4386825 | F17: ='Prêt Terme B'!F11 -> 4341600 | G17: ='Prêt Terme B'!G11 -> 4296375 | H17: ='Prêt Terme B'!H11 -> 4251150
A18: Total intérêts cash | B18: =SUM(B14:B17) -> 12434638 | C18: =SUM(C14:C17) -> 11917026 | D18: =SUM(D14:D17) -> 11364546 | E18: =SUM(E14:E17) -> 10806699 | F18: =SUM(F14:F17) -> 10239778 | G18: =SUM(G14:G17) -> 9660185.3 | H18: =SUM(H14:H17) -> 10430231
A20: Données pour ratios
A21: EBITDA | B21: 30000000 | C21: =B21*(1+5%) -> 31500000 | D21: =C21*(1+5%) -> 33075000 | E21: =D21*(1+5%) -> 34728750 | F21: =E21*(1+5%) -> 36465188 | G21: =F21*(1+5%) -> 38288447 | H21: =G21*(1+5%) -> 40202869
A22: CapEx | B22: 8000000 | C22: 8000000 | D22: 8000000 | E22: 8000000 | F22: 8000000 | G22: 8000000 | H22: 8000000
A23: Trésorerie fin d'année | B23: ='Flux de trésorerie'!B16 -> 0 | C23: ='Flux de trésorerie'!C16 -> 0 | D23: ='Flux de trésorerie'!D16 -> 2099357.1 | E23: ='Flux de trésorerie'!E16 -> 6948733.6 | F23: ='Flux de trésorerie'!F16 -> 14465629 | G23: ='Flux de trésorerie'!G16 -> 24570017 | H23: ='Flux de trésorerie'!H16 -> 0
A25: Ratios
A26: Couverture des intérêts | B26: =B21/B18 -> 2.4126155 | C26: =C21/C18 -> 2.6432768 | D26: =D21/D18 -> 2.9103671 | E26: =E21/E18 -> 3.2136316 | F26: =F21/F18 -> 3.5611308 | G26: =G21/G18 -> 3.9635313 | H26: =H21/H18 -> 3.8544563
A27: Endettement net / EBITDA | B27: =B11/B21 -> 7.3133333 | C27: =C11/C21 -> 6.5434921 | D27: =D11/D21 -> 5.8067954 | E27: =E11/E21 -> 5.121703 | F27: =F11/F21 -> 4.4828967 | G27: =G11/G21 -> 3.8857188 | H27: =H11/H21 -> 0.91247924
A28: DSCR | B28: =(B21 - B22) / (B18 + 'Flux de trésorerie'!B11) -> 0.80086341 | C28: =(C21 - C22) / (C18 + 'Flux de trésorerie'!C11) -> 0.87189649 | D28: =(D21 - D22) / (D18 + 'Flux de trésorerie'!D11) -> 0.94980125 | E28: =(E21 - E22) / (E18 + 'Flux de trésorerie'!E11) -> 1.0342977 | F28: =(F21 - F22) / (F18 + 'Flux de trésorerie'!F11) -> 1.1261972 | G28: =(G21 - G22) / (G18 + 'Flux de trésorerie'!G11) -> 1.2264565 | H28: =(H21 - H22) / (H18 + 'Flux de trésorerie'!H11) -> 0.38845332

Sheet Flux de trésorerie
A5: Année | B5: {=_xlfn.SEQUENCE(1,7,2026,1)} -> 2026 | C5: 2027 | D5: 2028 | E5: 2029 | F5: 2030 | G5: 2031 | H5: 2032
A6: Trésorerie début | B6: 200000 | C6: =B16 -> 0 | D6: =C16 -> 0 | E6: =D16 -> 2099357.1 | F6: =E16 -> 6948733.6 | G6: =F16 -> 14465629 | H6: =G16 -> 24570017
A7: Flux d'exploitation | B7: 12000000 | C7: 15000000 | D7: 18000000 | E7: 21000000 | F7: 24000000 | G7: 27000000 | H7: 30000000
A8: Flux d'investissement | B8: -500000 | C8: -600000 | D8: -700000 | E8: -800000 | F8: -900000 | G8: -1000000 | H8: -11000000
A9: Réserve de trésorerie obligatoire | B9: =Hypothèses!$B$34 -> 100000 | C9: =Hypothèses!$B$34 -> 100000 | D9: =Hypothèses!$B$34 -> 100000 | E9: =Hypothèses!$B$34 -> 100000 | F9: =Hypothèses!$B$34 -> 100000 | G9: =Hypothèses!$B$34 -> 100000 | H9: =Hypothèses!$B$34 -> 100000
A10: Disponible avant remboursement | B10: =B6+B7+B8-B9 -> 11600000 | C10: =C6+C7+C8-C9 -> 14300000 | D10: =D6+D7+D8-D9 -> 17200000 | E10: =E6+E7+E8-E9 -> 22199357 | F10: =F6+F7+F8-F9 -> 29948734 | G10: =G6+G7+G8-G9 -> 40365629 | H10: =H6+H7+H8-H9 -> 43470017
A11: Remboursements obligatoires (dette senior, TLB, mezz in fine) | B11: ='Dette senior'!B7 + 'Prêt Terme B'!B7 + 'Prêt Terme B'!B9 + 'Dette Mezzanine'!B10 -> 15035714 | C11: ='Dette senior'!C7+'Prêt Terme B'!C7+'Dette Mezzanine'!C10 -> 15035714 | D11: ='Dette senior'!D7+'Prêt Terme B'!D7+'Dette Mezzanine'!D10 -> 15035714 | E11: ='Dette senior'!E7+'Prêt Terme B'!E7+'Dette Mezzanine'!E10 -> 15035714 | F11: ='Dette senior'!F7+'Prêt Terme B'!F7+'Dette Mezzanine'!F10 -> 15035714 | G11: ='Dette senior'!G7+'Prêt Terme B'!G7+'Dette Mezzanine'!G10 -> 15035714 | H11: ='Dette senior'!H7+'Prêt Terme B'!H7+'Dette Mezzanine'!H10 -> 72469998
A12: Disponible après remboursements obligatoires | B12: =B10-B11 -> -3435714.3 | C12: =C10-C11 -> -735714.29 | D12: =D10-D11 -> 2164285.7 | E12: =E10-E11 -> 7163642.9 | F12: =F10-F11 -> 14913019 | G12: =G10-G11 -> 25329914 | H12: =H10-H11 -> -28999981
A13: Sweep (remboursement anticipé) | B13: =IF(B12>0, -B12*Hypothèses!$B$33, 0) -> 0 | C13: =IF(C12>0, -C12*Hypothèses!$B$33, 0) -> 0 | D13: =IF(D12>0, -D12*Hypothèses!$B$33, 0) -> -64928.571 | E13: =IF(E12>0, -E12*Hypothèses!$B$33, 0) -> -214909.29 | F13: =IF(F12>0, -F12*Hypothèses!$B$33, 0) -> -447390.58 | G13: =IF(G12>0, -G12*Hypothèses!$B$33, 0) -> -759897.43 | H13: =IF(H12>0, -H12*Hypothèses!$B$33, 0) -> 0
A14: Tirage sur ligne de crédit | B14: =IF(B12<0, -B12, 0) -> 3435714.3 | C14: =IF(C12<0, -C12, 0) -> 735714.29 | D14: =IF(D12<0, -D12, 0) -> 0 | E14: =IF(E12<0, -E12, 0) -> 0 | F14: =IF(F12<0, -F12, 0) -> 0 | G14: =IF(G12<0, -G12, 0) -> 0 | H14: =IF(H12<0, -H12, 0) -> 28999981
A15: Variation de trésorerie | B15: =B7+B8-B9-B11+B13+B14 -> -200000 | C15: =C7+C8-C9-C11+C13+C14 -> 0 | D15: =D7+D8-D9-D11+D13+D14 -> 2099357.1 | E15: =E7+E8-E9-E11+E13+E14 -> 4849376.4 | F15: =F7+F8-F9-F11+F13+F14 -> 7516895.1 | G15: =G7+G8-G9-G11+G13+G14 -> 10104388 | H15: =H7+H8-H9-H11+H13+H14 -> -24570017
A16: Trésorerie fin | B16: =B6+B15 -> 0 | C16: =C6+C15 -> 0 | D16: =D6+D15 -> 2099357.1 | E16: =E6+E15 -> 6948733.6 | F16: =F6+F15 -> 14465629 | G16: =G6+G15 -> 24570017 | H16: =H6+H15 -> 0
